jupyter_editor/__init__.py
jupyter_editor/operations.py
jupyter_editor/server.py
jupyter_editor/utils.py
jupyter_editor_mcp-0.2.2.dist-info/METADATA
jupyter_editor_mcp-0.2.2.dist-info/WHEEL
jupyter_editor_mcp-0.2.2.dist-info/entry_points.txt
jupyter_editor_mcp-0.2.2.dist-info/licenses/LICENSE
jupyter_editor_mcp-0.2.2.dist-info/RECORD
