Metadata-Version: 2.4
Name: jupyter-editor-mcp
Version: 0.2.2
Summary: Model Context Protocol server providing 29 specialized tools for programmatic Jupyter notebook editing with format preservation, batch operations, and no Jupyter server required
Project-URL: Homepage, https://github.com/jsamuel1/jupyter-editor-mcp
Project-URL: Documentation, https://github.com/jsamuel1/jupyter-editor-mcp#readme
Project-URL: Repository, https://github.com/jsamuel1/jupyter-editor-mcp
Project-URL: Issues, https://github.com/jsamuel1/jupyter-editor-mcp/issues
Project-URL: PyPI, https://pypi.org/project/jupyter-editor-mcp/
Author-email: Joshua Samuel <sauhsoj@amazon.com>
License: MIT
License-File: LICENSE
Keywords: editor,jupyter,mcp,model-context-protocol,notebook
Classifier: Development Status :: 4 - Beta
Classifier: Intended Audience :: Developers
Classifier: License :: OSI Approved :: MIT License
Classifier: Programming Language :: Python :: 3
Classifier: Programming Language :: Python :: 3.10
Classifier: Programming Language :: Python :: 3.11
Classifier: Programming Language :: Python :: 3.12
Classifier: Topic :: Software Development :: Libraries :: Python Modules
Requires-Python: >=3.10
Requires-Dist: fastmcp>=0.1.0
Requires-Dist: nbformat>=5.10.0
Provides-Extra: build
Requires-Dist: build>=1.0.0; extra == 'build'
Requires-Dist: twine>=4.0.0; extra == 'build'
Provides-Extra: dev
Requires-Dist: pytest-asyncio>=0.21.0; extra == 'dev'
Requires-Dist: pytest-cov>=4.0.0; extra == 'dev'
Requires-Dist: pytest>=7.0.0; extra == 'dev'
